saucisses_utils/factories/IdFactory.py
saucisses_utils/factories/__init__.py
saucisses_utils/models/Id.py
saucisses_utils/models/Stringable.py
saucisses_utils/models/__init__.py
saucisses_utils-0.1.2.dist-info/LICENSE.md
saucisses_utils-0.1.2.dist-info/METADATA
saucisses_utils-0.1.2.dist-info/WHEEL
saucisses_utils-0.1.2.dist-info/top_level.txt
saucisses_utils-0.1.2.dist-info/RECORD
