Metadata-Version: 2.1
Name: saucisses_utils
Version: 0.1.2
Summary: Saucisses Team project utils package
Home-page: https://github.com/saucisses-a-roulettes/saucisses_utils
Author: Saucisses Team
License: MIT License
Keywords: pip,bekindto,utils
License-File: LICENSE.md
